{"legislative_session": "2026", "identifier": "SB2107", "title": "RELATING TO LUNG CANCER SCREENING.", "from_organization": "~{\"classification\": \"upper\"}", "classification": ["bill"], "subject": ["Cigarettes", "DOH", "Educational Materials", "Lung Cancer Screening", "Retailers", "Signage", "Tobacco Products", "Written Notice"], "abstracts": [{"note": "description", "abstract": "Requires the Department of Health to develop by 12/31/2026, standardized educational materials relating to lung cancer screening and language on lung cancer screening information to be included in signage and written notices to be used by retailers of tobacco products.  Beginning 1/1/2027, requires retailers engaged in the retail sale of tobacco products to display signage on lung cancer screening at each point of sale and provide written notice on lung cancer screening to each buyer of a tobacco product."}], "other_titles": [], "other_identifiers": [], "actions": [{"description": "Pending Introduction.", "date": "2026-01-14", "organization_id": "~{\"classification\": \"upper\"}", "classification": [], "related_entities": []}], "sponsorships": [{"name": "GABBARD", "classification": "primary", "entity_type": "person", "primary": true, "person_id": "~{\"name\": \"GABBARD\"}", "organization_id": null}, {"name": "CHANG", "classification": "primary", "entity_type": "person", "primary": true, "person_id": "~{\"name\": \"CHANG\"}", "organization_id": null}, {"name": "HASHIMOTO", "classification": "primary", "entity_type": "person", "primary": true, "person_id": "~{\"name\": \"HASHIMOTO\"}", "organization_id": null}, {"name": "RHOADS", "classification": "primary", "entity_type": "person", "primary": true, "person_id": "~{\"name\": \"RHOADS\"}", "organization_id": null}, {"name": "SAN BUENAVENTURA", "classification": "primary", "entity_type": "person", "primary": true, "person_id": "~{\"name\": \"SAN BUENAVENTURA\"}", "organization_id": null}, {"name": "Fukunaga", "classification": "cosponsor", "entity_type": "person", "primary": false, "person_id": "~{\"name\": \"Fukunaga\"}", "organization_id": null}, {"name": "Moriwaki", "classification": "cosponsor", "entity_type": "person", "primary": false, "person_id": "~{\"name\": \"Moriwaki\"}", "organization_id": null}], "related_bills": [], "versions": [{"note": "SB2107", "links": [{"url": "https://data.capitol.hawaii.gov/sessions/session2026/bills/SB2107_.HTM", "media_type": "text/html"}, {"url": "https://data.capitol.hawaii.gov/sessions/session2026/bills/SB2107_.PDF", "media_type": "application/pdf"}], "date": "", "classification": ""}], "documents": [], "citations": [], "sources": [{"url": "https://capitol.hawaii.gov/session/measure_indiv.aspx?billtype=SB&billnumber=2107&year=2026", "note": ""}], "extras": {}, "jurisdiction": {"id": "ocd-jurisdiction/country:us/state:hi/government", "name": "Hawaii", "classification": "state", "division_id": "ocd-division/country:us/state:hi"}, "scraped_at": "2026-02-13T08:36:25+00:00", "_id": "152bd50a-08b7-11f1-9192-66daaf070ac1"}