{"legislative_session": "2026", "identifier": "SB2324", "title": "RELATING TO CONDOMINIUMS.", "from_organization": "~{\"classification\": \"upper\"}", "classification": ["bill"], "subject": ["Agricultural District", "Condominiums", "Neighborhood Boards", "Project", "Registration"], "abstracts": [{"note": "description", "abstract": "For purposes of registering a condominium project in an agricultural district, (1) lowers the threshold from projects with five units to projects with two units for which a signed statement from a county is required and (2) requires a signed statement from the neighborhood board, if applicable."}], "other_titles": [], "other_identifiers": [], "actions": [{"description": "Pending Introduction.", "date": "2026-01-15", "organization_id": "~{\"classification\": \"upper\"}", "classification": [], "related_entities": []}], "sponsorships": [{"name": "GABBARD", "classification": "primary", "entity_type": "person", "primary": true, "person_id": "~{\"name\": \"GABBARD\"}", "organization_id": null}, {"name": "RICHARDS", "classification": "primary", "entity_type": "person", "primary": true, "person_id": "~{\"name\": \"RICHARDS\"}", "organization_id": null}, {"name": "SAN BUENAVENTURA", "classification": "primary", "entity_type": "person", "primary": true, "person_id": "~{\"name\": \"SAN BUENAVENTURA\"}", "organization_id": null}], "related_bills": [], "versions": [{"note": "SB2324", "links": [{"url": "https://data.capitol.hawaii.gov/sessions/session2026/bills/SB2324_.HTM", "media_type": "text/html"}, {"url": "https://data.capitol.hawaii.gov/sessions/session2026/bills/SB2324_.PDF", "media_type": "application/pdf"}], "date": "", "classification": ""}], "documents": [], "citations": [], "sources": [{"url": "https://capitol.hawaii.gov/session/measure_indiv.aspx?billtype=SB&billnumber=2324&year=2026", "note": ""}], "extras": {}, "jurisdiction": {"id": "ocd-jurisdiction/country:us/state:hi/government", "name": "Hawaii", "classification": "state", "division_id": "ocd-division/country:us/state:hi"}, "scraped_at": "2026-02-22T08:25:09+00:00", "_id": "0013a298-0fc8-11f1-a210-7ae1429e38ea"}