{"legislative_session": "2026", "identifier": "SB2016", "title": "RELATING TO LEGISLATIVE VACANCIES.", "from_organization": "~{\"classification\": \"upper\"}", "classification": ["bill"], "subject": ["Appointments", "Legislature", "Representatives", "Senators", "Term", "Vacancies"], "abstracts": [{"note": "description", "abstract": "Establishes that if the death or permanent incapacitation of the prior incumbent leaves a legislative seat vacant before a primary election, but after the close of filing for candidacy in that election, and the prior incumbent's name was the only name on any ballot for that seat for that election, the Governor's appointment of a replacement shall be valid for both the unexpired term and the succeeding term."}], "other_titles": [], "other_identifiers": [], "actions": [{"description": "Pending Introduction.", "date": "2026-01-14", "organization_id": "~{\"classification\": \"upper\"}", "classification": [], "related_entities": []}], "sponsorships": [{"name": "INOUYE", "classification": "primary", "entity_type": "person", "primary": true, "person_id": "~{\"name\": \"INOUYE\"}", "organization_id": null}], "related_bills": [], "versions": [{"note": "SB2016", "links": [{"url": "https://data.capitol.hawaii.gov/sessions/session2026/bills/SB2016_.HTM", "media_type": "text/html"}, {"url": "https://data.capitol.hawaii.gov/sessions/session2026/bills/SB2016_.PDF", "media_type": "application/pdf"}], "date": "", "classification": ""}], "documents": [], "citations": [], "sources": [{"url": "https://capitol.hawaii.gov/session/measure_indiv.aspx?billtype=SB&billnumber=2016&year=2026", "note": ""}], "extras": {}, "jurisdiction": {"id": "ocd-jurisdiction/country:us/state:hi/government", "name": "Hawaii", "classification": "state", "division_id": "ocd-division/country:us/state:hi"}, "scraped_at": "2026-02-09T08:43:20+00:00", "_id": "62ee1ae0-0593-11f1-a55f-92b7de160456"}