{"legislative_session": "2026", "identifier": "SR195", "title": "INFORMING THE HOUSE AND GOVERNOR THAT THE SENATE IS READY TO ADJOURN SINE DIE.", "from_organization": "~{\"classification\": \"upper\"}", "classification": ["resolution"], "subject": ["Adjourn Sine Die"], "abstracts": [], "other_titles": [], "other_identifiers": [{"identifier": "ocd-bill-hi-2026-sr195"}], "actions": [{"description": "Received notice of Adoption (Sen. Com. No. 823).", "date": "2026-05-12", "organization_id": "~{\"classification\": \"lower\"}", "classification": ["receipt"], "related_entities": []}, {"description": "Adopted.", "date": "2026-05-08", "organization_id": "~{\"classification\": \"upper\"}", "classification": ["passage"], "related_entities": []}, {"description": "Offered.", "date": "2026-05-08", "organization_id": "~{\"classification\": \"upper\"}", "classification": ["introduction"], "related_entities": []}], "sponsorships": [{"name": "KANUHA", "classification": "primary", "entity_type": "person", "primary": true, "person_id": "~{\"name\": \"KANUHA\"}", "organization_id": null}], "related_bills": [], "versions": [{"note": "SR195", "links": [{"url": "https://data.capitol.hawaii.gov/sessions/session2026/bills/SR195_.HTM", "media_type": "text/html"}, {"url": "https://data.capitol.hawaii.gov/sessions/session2026/bills/SR195_.PDF", "media_type": "application/pdf"}], "date": "", "classification": ""}], "documents": [], "citations": [], "sources": [{"url": "https://capitol.hawaii.gov/session/measure_indiv.aspx?billtype=SR&billnumber=195&year=2026", "note": ""}], "extras": {}, "jurisdiction": {"id": "ocd-jurisdiction/country:us/state:hi/government", "name": "Hawaii", "classification": "state", "division_id": "ocd-division/country:us/state:hi"}, "scraped_at": "2026-07-02T22:34:15+00:00", "_id": "280aacc4-7666-11f1-88f8-26d268f71124"}