{"legislative_session": "2026", "identifier": "HB1604", "title": "RELATING TO AGRICULTURAL WORKFORCE HOUSING.", "from_organization": "~{\"classification\": \"lower\"}", "classification": ["bill"], "subject": ["Agricultural Workforce Housing Working Group", "Appropriation ($)", "DAB", "Report"], "abstracts": [{"note": "description", "abstract": "Establishes an Agricultural Workforce Housing Working Group within the Department of Agriculture and Biosecurity to address the shortage and challenges of agricultural workforce housing in the State.  Requires reports to the Legislature.  Appropriates funds."}], "other_titles": [], "other_identifiers": [], "actions": [{"description": "Prefiled.", "date": "2026-01-16", "organization_id": "~{\"classification\": \"lower\"}", "classification": [], "related_entities": []}], "sponsorships": [{"name": "CHUN", "classification": "primary", "entity_type": "person", "primary": true, "person_id": "~{\"name\": \"CHUN\"}", "organization_id": null}, {"name": "KAHALOA", "classification": "primary", "entity_type": "person", "primary": true, "person_id": "~{\"name\": \"KAHALOA\"}", "organization_id": null}, {"name": "LOWEN", "classification": "primary", "entity_type": "person", "primary": true, "person_id": "~{\"name\": \"LOWEN\"}", "organization_id": null}, {"name": "MATSUMOTO", "classification": "primary", "entity_type": "person", "primary": true, "person_id": "~{\"name\": \"MATSUMOTO\"}", "organization_id": null}, {"name": "PERRUSO", "classification": "primary", "entity_type": "person", "primary": true, "person_id": "~{\"name\": \"PERRUSO\"}", "organization_id": null}, {"name": "QUINLAN", "classification": "primary", "entity_type": "person", "primary": true, "person_id": "~{\"name\": \"QUINLAN\"}", "organization_id": null}, {"name": "Kusch", "classification": "cosponsor", "entity_type": "person", "primary": false, "person_id": "~{\"name\": \"Kusch\"}", "organization_id": null}], "related_bills": [], "versions": [{"note": "HB1604", "links": [{"url": "https://data.capitol.hawaii.gov/sessions/session2026/bills/HB1604_.HTM", "media_type": "text/html"}, {"url": "https://data.capitol.hawaii.gov/sessions/session2026/bills/HB1604_.PDF", "media_type": "application/pdf"}], "date": "", "classification": ""}], "documents": [], "citations": [], "sources": [{"url": "https://capitol.hawaii.gov/session/measure_indiv.aspx?billtype=HB&billnumber=1604&year=2026", "note": ""}], "extras": {}, "jurisdiction": {"id": "ocd-jurisdiction/country:us/state:hi/government", "name": "Hawaii", "classification": "state", "division_id": "ocd-division/country:us/state:hi"}, "scraped_at": "2026-02-10T08:43:51+00:00", "_id": "a03751cc-065c-11f1-b5c3-2ae471d40b6c"}